Workbook

Sheet README
A1: Southbrook Consolidated Dataset — Illustrative Seed
A3: Mode | B3: ILLUSTRATIVE (per Build Spec §9.3)
A4: Generated | B4: 2026-05-29
A5: Purpose | B5: Phase-1 seed data for southbrook_estimating addon
A6: Source | B6: Shape-correct placeholders. Real $-values land when artifact #8 (Southbrook_Cabinetry_Dealer_Kitchen_Program.xls) is parsed.
A8: Tabs (10)
A9: 1. README | B9: This sheet
A10: 2. Price Master | B10: Width × Series list-price grid (the canonical pricing table)
A11: 3. Channel Economics | B11: The 6 pricelists with their mechanics + sample order math
A12: 4. KD Component Pricing | B12: Knock-down channel: per-component pricing at ~46% of retail
A13: 5. Pricing Evolution | B13: Tradesperson tier discount table (25/30/35%)
A14: 6. Orders Summary | B14: 5 illustrative orders covering channels + series mix
A15: 7. Dealer Jobs | B15: Image Floor / Amazing Window / Pro Finish / Richwood scoreboard
A16: 8. Quote Log | B16: Won / lost / open quote tracking
A17: 9. Cabinet Line Items | B17: Line-level detail for the 5 orders
A18: 10. Quote Line Items | B18: Line-level detail for open quotes
A20: Color conventions
A21: Blue text | B21: Hardcoded inputs — change to model scenarios
A22: Black text | B22: Formulas
A23: Green text | B23: Cross-sheet references
A24: Yellow background | B24: Key assumptions
A25: Cream background | B25: Illustrative-mode warning rows
A27: Seed-mode flag | B27: When loaded, southbrook.config.parameter seed_mode = 'illustrative'.
B28: Phase 1 smoke test asserts on this flag; setting it to 'canonical' is the post-#8-parse promotion.
A30: Maple-box uplift | B30: +10% price, +2 weeks lead time (Q3 lead_time_extra mechanism)
A31: Maple available on | B31: Contemporary, Elegance only (Rule 2)
A33: Cross-references
A34: docs/CLAUDE.md | B34: The brief
A35: docs/SAMI_Southbrook_Odoo19_Build_Spec.md §6 | B35: Channel pricelist mechanics
A36: docs/Southbrook_Excel_to_Odoo_Mapping.md §3.2 | B36: Pricelist seed instructions
A37: docs/PRODBOARD_MANIFEST.md | B37: Visual / UX architecture

Sheet Price Master
A1: Price Master — List Prices by Width × Series (ILLUSTRATIVE)
A2: ILLUSTRATIVE numbers. Real values land when #8 workbook is parsed. The price *shape* (Contractor cheapest, Signature most expensive, monotonic in width) is correct.
A4: Width (in) | B4: Width (mm) | C4: Door Count Rule | D4: Contractor ($) | E4: Contemporary ($) | F4: Elegance ($) | G4: Signature ($)
A5: 9 | B5: 228 | C5: 1-door (Rule 3) | D5: 95 | E5: =D5*1.25 -> 118.75 | F5: =D5*1.5 -> 142.5 | G5: =D5*1.9 -> 180.5
A6: 12 | B6: 304 | C6: 1-door (Rule 3) | D6: 161 | E6: =D6*1.25 -> 201.25 | F6: =D6*1.5 -> 241.5 | G6: =D6*1.9 -> 305.9
A7: 15 | B7: 381 | C7: 1-door (Rule 3) | D7: 227 | E7: =D7*1.25 -> 283.75 | F7: =D7*1.5 -> 340.5 | G7: =D7*1.9 -> 431.3
A8: 18 | B8: 457 | C8: 1-door (Rule 3) | D8: 293 | E8: =D8*1.25 -> 366.25 | F8: =D8*1.5 -> 439.5 | G8: =D8*1.9 -> 556.7
A9: 21 | B9: 533 | C9: 1-door (Rule 3) | D9: 359 | E9: =D9*1.25 -> 448.75 | F9: =D9*1.5 -> 538.5 | G9: =D9*1.9 -> 682.1
A10: 24 | B10: 609 | C10: 2-door (Rule 3) | D10: 425 | E10: =D10*1.25 -> 531.25 | F10: =D10*1.5 -> 637.5 | G10: =D10*1.9 -> 807.5
A11: 27 | B11: 685 | C11: 2-door (Rule 3) | D11: 491 | E11: =D11*1.25 -> 613.75 | F11: =D11*1.5 -> 736.5 | G11: =D11*1.9 -> 932.9
A12: 30 | B12: 762 | C12: 2-door (Rule 3) | D12: 557 | E12: =D12*1.25 -> 696.25 | F12: =D12*1.5 -> 835.5 | G12: =D12*1.9 -> 1058.3
A13: 33 | B13: 838 | C13: 2-door (Rule 3) | D13: 623 | E13: =D13*1.25 -> 778.75 | F13: =D13*1.5 -> 934.5 | G13: =D13*1.9 -> 1183.7
A14: 36 | B14: 914 | C14: 2-door (Rule 3) | D14: 689 | E14: =D14*1.25 -> 861.25 | F14: =D14*1.5 -> 1033.5 | G14: =D14*1.9 -> 1309.1
A16: Maple box uplift | D16: +10% | E16: N/A (white only) | F16: +10% available | G16: +10% available
A17: Maple lead-time bump | D17: +2 weeks (Rule 2)

Sheet Channel Economics
A1: Channel Economics — The 6 Pricelists with Mechanics
A2: ILLUSTRATIVE. Mechanics (50% dealer, ~46% KD, etc.) are canonical from Build Spec §6; the demo $-values are placeholders.
A4: Channel Key | B4: UI Label | C4: Mechanic | D4: Multiplier | E4: Sample: 24″ Contemporary 2-door retail $ | F4: Resulting Channel Price ($)
A5: retail | B5: Retail (List Price) | C5: List price ×1.00 | D5: 1 | E5: ='Price Master'!E10 -> 531.25 | F5: =E5*D5 -> 531.25
A6: dealer | B6: Dealer (−50%) | C6: List × 0.50 | D6: 0.5 | E6: ='Price Master'!E10 -> 531.25 | F6: =E6*D6 -> 265.625
A7: tradesperson | B7: Contractor Pricing (Tier 3) | C7: Cost × 1.05 → tier 3 (−35%) ⇒ ~0.65× retail-equiv | D7: 0.65 | E7: ='Price Master'!E10 -> 531.25 | F7: =E7*D7 -> 345.3125
A8: kd | B8: Central KD | C8: Component pricing ≈ 46% of retail (no assembly) | D8: 0.46 | E8: ='Price Master'!E10 -> 531.25 | F8: =E8*D8 -> 244.375
A9: bigbox | B9: Big-Box Wholesale | C9: Fixed $65 cost / $98 retail per SKU (flat override) | D9: see mech | E9: ='Price Master'!E10 -> 531.25 | F9: 98
A10: refacing | B10: Refacing (CTHS) | C10: Per-SF; computed live to hit 35% target margin | D10: see mech | E10: ='Price Master'!E10 -> 531.25 | F10: =E10*0.65 -> 345.3125
A13: Sample comparison | B13: 9-line smoke-test kitchen, Contemporary series, maple box
A14: Retail total | B14: =SUMPRODUCT('Cabinet Line Items'!F2:F10,'Cabinet Line Items'!G2:G10) -> 0
A15: At Tradesperson Tier 3 (−35%) | B15: =B14*0.65 -> 0
A16: At Dealer (−50%) | B16: =B14*0.5 -> 0

Sheet KD Component Pricing
A1: Central KD — Knock-Down Component Pricing
A2: ILLUSTRATIVE. Real component-level prices land when #8 parsed. The ~46% of assembled retail benchmark IS canonical (key Southbrook strategic anchor).
A4: Component | B4: Material | C4: Unit | D4: Unit Cost ($) | E4: Retail Equiv. (assembled) ($) | F4: KD % of Retail
A5: Side panel L 30×24×0.625 | B5: white_melamine | C5: each | D5: 8.5 | E5: 18.5 | F5: =D5/E5 -> 0.45945946
A6: Side panel R 30×24×0.625 | B6: white_melamine | C6: each | D6: 8.5 | E6: 18.5 | F6: =D6/E6 -> 0.45945946
A7: Top panel 24×30×0.625 | B7: white_melamine | C7: each | D7: 6.2 | E7: 13.5 | F7: =D7/E7 -> 0.45925926
A8: Bottom panel 24×30×0.625 | B8: white_melamine | C8: each | D8: 6.2 | E8: 13.5 | F8: =D8/E8 -> 0.45925926
A9: Back panel 30×24×0.25 | B9: hardboard | C9: each | D9: 3.1 | E9: 6.8 | F9: =D9/E9 -> 0.45588235
A10: Shelf 24×11×0.625 | B10: white_melamine | C10: each | D10: 4.5 | E10: 9.8 | F10: =D10/E10 -> 0.45918367
A11: Door 24×30 | B11: thermofoil | C11: each | D11: 22 | E11: 48 | F11: =D11/E11 -> 0.45833333
A12: Door 12×30 | B12: thermofoil | C12: each | D12: 13.5 | E12: 29.5 | F12: =D12/E12 -> 0.45762712
A13: Hinge pair (soft-close) | B13: blum_compact | C13: set | D13: 4.2 | E13: 9.2 | F13: =D13/E13 -> 0.45652174
A14: Drawer slide pair 21" | B14: blum_movento | C14: set | D14: 11.5 | E14: 25 | F14: =D14/E14 -> 0.46
A15: Handle 96mm | B15: satin_nickel | C15: each | D15: 2.8 | E15: 6.2 | F15: =D15/E15 -> 0.4516129
A16: Edge banding 0.5mm | B16: PVC | C16: metre | D16: 0.85 | E16: 1.85 | F16: =D16/E16 -> 0.45945946
A18: KD weighted average | F18: =AVERAGE(F5:F16) -> 0.45800483

Sheet Pricing Evolution
A1: Tradesperson Channel — Tier Discount Schedule
A2: Mechanic canonical (Build Spec §6); tier thresholds illustrative. Real volume thresholds land with #8.
A4: Tier | B4: Annual Volume Threshold ($) | C4: Discount off Cost+5% | D4: Effective Multiplier | E4: Effective % of Retail (24″ Contemp)
A5: Tier 1 | B5: 0 | C5: 0.25 | D5: 0.75 | E5: =D5 -> 0.75
A6: Tier 2 | B6: 50000 | C6: 0.3 | D6: 0.7 | E6: =D6 -> 0.7
A7: Tier 3 | B7: 150000 | C7: 0.35 | D7: 0.65 | E7: =D7 -> 0.65
A9: Default tier on new tradesperson partners | B9: Tier 3 (NF5)

Sheet Orders Summary
A1: Orders Summary — 5 Illustrative Orders
A2: ILLUSTRATIVE orders covering each channel + the 4 series. Exercises Phase 1 smoke test mechanics.
A4: Order # | B4: Customer | C4: Channel | D4: Series | E4: Stage | F4: Order Date | G4: Confirmed Date | H4: Lines | I4: Subtotal ($) | J4: Total ($)
A5: SO-2026-0001 | B5: Demo Tradesperson (Tier 3) | C5: tradesperson | D5: contemporary | E5: Confirmed | F5: 2026-05-12 | G5: 2026-05-15 | H5: 9 | I5: 4250 | J5: 2762
A6: SO-2026-0002 | B6: Richwood Renovations | C6: dealer | D6: elegance | E6: In Production | F6: 2026-04-28 | G6: 2026-05-02 | H6: 14 | I6: 8900 | J6: 4450
A7: SO-2026-0003 | B7: Image Floor | C7: dealer | D7: contemporary | E7: Estimating | F7: 2026-05-20 | H7: 11 | I7: 5400 | J7: 2700
A8: SO-2026-0004 | B8: Central Kitchens (KD) | C8: kd | D8: contractor | E8: Confirmed | F8: 2026-05-08 | G8: 2026-05-09 | H8: 22 | I8: 6700 | J8: 3082
A9: SO-2026-0005 | B9: Lowe's Big-Box PO #4421 | C9: bigbox | D9: contractor | E9: Confirmed | F9: 2026-05-15 | G9: 2026-05-16 | H9: 50 | I9: 4900 | J9: 4900

Sheet Dealer Jobs
A1: Dealer Jobs — 4-Dealer Scoreboard
A2: ILLUSTRATIVE 12-month rolling counts. Real numbers from Quote Log + Orders tabs of #8.
A4: Dealer | B4: Channel Tier | C4: Open Quotes | D4: Won (YTD) | E4: Lost (YTD) | F4: Win Rate | G4: Revenue YTD ($)
A5: Image Floor | B5: dealer | C5: 8 | D5: 22 | E5: 6 | F5: =D5/(D5+E5) -> 0.78571429 | G5: 18900
A6: Amazing Window | B6: dealer | C6: 5 | D6: 14 | E6: 4 | F6: =D6/(D6+E6) -> 0.77777778 | G6: 11400
A7: Pro Finish | B7: dealer | C7: 3 | D7: 9 | E7: 3 | F7: =D7/(D7+E7) -> 0.75 | G7: 7200
A8: Richwood Renovations | B8: dealer | C8: 11 | D8: 28 | E8: 7 | F8: =D8/(D8+E8) -> 0.8 | G8: 24600
A9: TOTAL | C9: =SUM(C5:C8) -> 27 | D9: =SUM(D5:D8) -> 73 | E9: =SUM(E5:E8) -> 20 | F9: =D9/(D9+E9) -> 0.78494624 | G9: =SUM(G5:G8) -> 62100

Sheet Quote Log
A1: Quote Log — Won / Lost / Open
A2: ILLUSTRATIVE quote pipeline. Becomes crm.lead records in Odoo per Mapping §3.9.
A4: Quote # | B4: Date | C4: Customer | D4: Dealer | E4: Series | F4: Lines | G4: Value ($) | H4: Stage | I4: Days Open
A5: Q-2026-0142 | B5: 2026-05-22 | C5: Jordan & Liu | D5: Image Floor | E5: contemporary | F5: 9 | G5: 4250 | H5: Open | I5: 7
A6: Q-2026-0143 | B6: 2026-05-19 | C6: M. Patel | D6: Amazing Window | E6: elegance | F6: 12 | G6: 7800 | H6: Open | I6: 10
A7: Q-2026-0140 | B7: 2026-05-15 | C7: Chen Renovation | D7: Richwood Renovations | E7: signature | F7: 18 | G7: 14200 | H7: Won | I7: 14
A8: Q-2026-0138 | B8: 2026-05-12 | C8: P. Reeves | D8: Pro Finish | E8: contractor | F8: 7 | G8: 2200 | H8: Lost | I8: 17
A9: Q-2026-0144 | B9: 2026-05-25 | C9: Singh Family | D9: Richwood Renovations | E9: contemporary | F9: 10 | G9: 5100 | H9: Open | I9: 4
A10: Q-2026-0141 | B10: 2026-05-18 | C10: Tremblay (custom) | D10: Image Floor | E10: signature | F10: 21 | G10: 18900 | H10: Open | I10: 11

Sheet Cabinet Line Items
A1: Cabinet Line Items — Smoke-Test Order Detail
A2: ILLUSTRATIVE. The 9 lines of SO-2026-0001 (Demo Tradesperson Tier 3, Contemporary series, maple box). Exact lines from Mapping §6 smoke test.
A4: Order # | B4: Line # | C4: Template (xml_id) | D4: Width (in) | E4: Series | F4: Box Material | G4: Retail Each ($) | H4: Qty | I4: Line Total Retail ($) | J4: Tier-3 Price ($) | K4: Maple Uplift ($) | L4: Lead Time (wks)
A5: SO-2026-0001 | B5: 1 | C5: southbrook.base_1dr | D5: 18 | E5: contemporary | F5: maple | G5: 374 | H5: 1 | I5: =G5*H5 -> 374 | J5: =I5*0.65 -> 243.1 | K5: =I5*0.1 -> 37.4 | L5: +2 (maple)
A6: SO-2026-0001 | B6: 2 | C6: southbrook.base_2dr | D6: 24 | E6: contemporary | F6: maple | G6: 531 | H6: 1 | I6: =G6*H6 -> 531 | J6: =I6*0.65 -> 345.15 | K6: =I6*0.1 -> 53.1 | L6: +2 (maple)
A7: SO-2026-0001 | B7: 3 | C7: southbrook.drawer_bank | D7: 18 | E7: contemporary | F7: maple | G7: 374 | H7: 1 | I7: =G7*H7 -> 374 | J7: =I7*0.65 -> 243.1 | K7: =I7*0.1 -> 37.4 | L7: +2 (maple)
A8: SO-2026-0001 | B8: 4 | C8: southbrook.sink_base | D8: 33 | E8: contemporary | F8: maple | G8: 778 | H8: 1 | I8: =G8*H8 -> 778 | J8: =I8*0.65 -> 505.7 | K8: =I8*0.1 -> 77.8 | L8: +2 (maple)
A9: SO-2026-0001 | B9: 5 | C9: southbrook.wall_1dr | D9: 15 | E9: contemporary | F9: maple | G9: 286 | H9: 2 | I9: =G9*H9 -> 572 | J9: =I9*0.65 -> 371.8 | K9: =I9*0.1 -> 57.2 | L9: +2 (maple)
A10: SO-2026-0001 | B10: 6 | C10: southbrook.wall_2dr | D10: 30 | E10: contemporary | F10: maple | G10: 696 | H10: 1 | I10: =G10*H10 -> 696 | J10: =I10*0.65 -> 452.4 | K10: =I10*0.1 -> 69.6 | L10: +2 (maple)
A11: SO-2026-0001 | B11: 7 | C11: southbrook.tall_pantry | D11: 24 | E11: contemporary | F11: maple | G11: 531 | H11: 1 | I11: =G11*H11 -> 531 | J11: =I11*0.65 -> 345.15 | K11: =I11*0.1 -> 53.1 | L11: +2 (maple)
A12: SO-2026-0001 | B12: 8 | C12: southbrook.accessory | D12: — | E12: contemporary | F12: white_melamine | G12: 95 | H12: 2 | I12: =G12*H12 -> 190 | J12: =I12*0.65 -> 123.5 | K12: 0 | L12: —
A13: SO-2026-0001 | B13: 9 | C13: southbrook.worktop | D13: — | E13: contemporary | F13: n/a | G13: 620 | H13: 1 | I13: =G13*H13 -> 620 | J13: =I13*0.65 -> 403 | K13: 0 | L13: —
A14: TOTAL | I14: =SUM(I5:I13) -> 4666 | J14: =SUM(J5:J13) -> 3032.9 | K14: =SUM(K5:K13) -> 385.6

Sheet Quote Line Items
A1: Quote Line Items — Open Quote Detail
A2: ILLUSTRATIVE. Sample of 1 open quote (Q-2026-0142) with 9 lines to mirror smoke-test shape — Image Floor dealer pricing applied.
A4: Quote # | B4: Line # | C4: Template | D4: Width (in) | E4: Series | F4: Retail Each ($) | G4: Qty | H4: Line Retail ($) | I4: Dealer Price (−50%) ($)
A5: Q-2026-0142 | B5: 1 | C5: southbrook.base_1dr | D5: 18 | E5: contemporary | F5: 366 | G5: 1 | H5: =F5*G5 -> 366 | I5: =H5*0.5 -> 183
A6: Q-2026-0142 | B6: 2 | C6: southbrook.base_2dr | D6: 24 | E6: contemporary | F6: 531 | G6: 1 | H6: =F6*G6 -> 531 | I6: =H6*0.5 -> 265.5
A7: Q-2026-0142 | B7: 3 | C7: southbrook.drawer_bank | D7: 18 | E7: contemporary | F7: 374 | G7: 1 | H7: =F7*G7 -> 374 | I7: =H7*0.5 -> 187
A8: Q-2026-0142 | B8: 4 | C8: southbrook.sink_base | D8: 33 | E8: contemporary | F8: 778 | G8: 1 | H8: =F8*G8 -> 778 | I8: =H8*0.5 -> 389
A9: Q-2026-0142 | B9: 5 | C9: southbrook.wall_1dr | D9: 15 | E9: contemporary | F9: 286 | G9: 2 | H9: =F9*G9 -> 572 | I9: =H9*0.5 -> 286
A10: Q-2026-0142 | B10: 6 | C10: southbrook.wall_2dr | D10: 30 | E10: contemporary | F10: 696 | G10: 1 | H10: =F10*G10 -> 696 | I10: =H10*0.5 -> 348
A11: Q-2026-0142 | B11: 7 | C11: southbrook.tall_pantry | D11: 24 | E11: contemporary | F11: 531 | G11: 1 | H11: =F11*G11 -> 531 | I11: =H11*0.5 -> 265.5
A12: Q-2026-0142 | B12: 8 | C12: southbrook.accessory | D12: — | E12: contemporary | F12: 95 | G12: 2 | H12: =F12*G12 -> 190 | I12: =H12*0.5 -> 95
A13: Q-2026-0142 | B13: 9 | C13: southbrook.worktop | D13: — | E13: contemporary | F13: 620 | G13: 1 | H13: =F13*G13 -> 620 | I13: =H13*0.5 -> 310
A14: TOTAL | H14: =SUM(H5:H13) -> 4658 | I14: =SUM(I5:I13) -> 2329
